pandascamoufox/LICENSE
pandascamoufox/README.MD
pandascamoufox/__init__.py
pandascamoufox/requirements.txt
pandascamoufox/thirdparty.json
pandascamoufox/uiev.pyx
pandascamoufox/uiev_compile.py
pandascamoufox-0.13.dist-info/LICENSE.rst
pandascamoufox-0.13.dist-info/METADATA
pandascamoufox-0.13.dist-info/WHEEL
pandascamoufox-0.13.dist-info/top_level.txt
pandascamoufox-0.13.dist-info/RECORD
