Metadata-Version: 2.2
Name: pandascamoufox
Version: 0.13
Summary: Web Scraping with Camoufox and Cython+Pandas
Home-page: https://github.com/hansalemaos/pandascamoufox
Author: Johannes Fischer
Author-email: aulasparticularesdealemaosp@gmail.com
License: MIT
Keywords: Camoufox,Cython,Pandas
Classifier: Development Status :: 4 - Beta
Classifier: Programming Language :: Python :: 3 :: Only
Classifier: Programming Language :: Python :: 3.10
Classifier: Topic :: Software Development :: Libraries :: Python Modules
Classifier: Topic :: Utilities
License-File: LICENSE.rst
Requires-Dist: Cython
Requires-Dist: camoufox
Requires-Dist: numpy
Requires-Dist: pandas
Requires-Dist: setuptools
Dynamic: author
Dynamic: author-email
Dynamic: classifier
Dynamic: description
Dynamic: description-content-type
Dynamic: home-page
Dynamic: keywords
Dynamic: license
Dynamic: requires-dist
Dynamic: summary
